app/__init__.py
app/main_task.py
app/sub_task_1/__init__.py
app/sub_task_1/helpers.py
app/sub_task_1/sub_task_1.py
app/sub_task_2/__init__.py
app/sub_task_2/helpers.py
app/sub_task_2/sub_task_2.py
magnifi_base_template-0.0.1.dist-info/METADATA
magnifi_base_template-0.0.1.dist-info/WHEEL
magnifi_base_template-0.0.1.dist-info/top_level.txt
magnifi_base_template-0.0.1.dist-info/RECORD
