Metadata-Version: 2.1
Name: magnifi-base-template
Version: 0.0.1
Summary: Base project template
Home-page: UNKNOWN
Author: Nick Wight
Author-email: <nick.wight@mymagnifi.org>
License: UNKNOWN
Keywords: magnifi,templates
Platform: UNKNOWN
Classifier: Development Status :: 1 - Planning
Classifier: Intended Audience :: Developers
Classifier: Programming Language :: Python :: 3
Classifier: Operating System :: Unix
Classifier: Operating System :: MacOS :: MacOS X
Classifier: Operating System :: Microsoft :: Windows
